chromadbx/__init__.py
chromadbx/clients/__init__.py
chromadbx/core/__init__.py
chromadbx/core/ids.py
chromadbx/core/queries.py
chromadbx/core/types.py
chromadbx/embeddings/__init__.py
chromadbx/embeddings/cloudflare.py
chromadbx/embeddings/google.py
chromadbx/embeddings/llamacpp.py
chromadbx/embeddings/mistral.py
chromadbx/embeddings/nomic.py
chromadbx/embeddings/onnx.py
chromadbx/embeddings/spacy.py
chromadbx/embeddings/together.py
chromadbx/reranking/__init__.py
chromadbx/reranking/cohere.py
chromadbx/reranking/utils.py
chromadbx-0.1.0.dist-info/LICENSE.md
chromadbx-0.1.0.dist-info/METADATA
chromadbx-0.1.0.dist-info/WHEEL
chromadbx-0.1.0.dist-info/RECORD
