Metadata-Version: 2.3
Name: chromadbx
Version: 0.1.0
Summary: A collection of experimental Chroma extensions.
Author: Trayan Azarov
Author-email: trayan.azarov@amikos.tech
Requires-Python: >=3.9,<3.13
Classifier: Programming Language :: Python :: 3
Classifier: Programming Language :: Python :: 3.9
Classifier: Programming Language :: Python :: 3.10
Classifier: Programming Language :: Python :: 3.11
Classifier: Programming Language :: Python :: 3.12
Provides-Extra: core
Provides-Extra: embeddings
Provides-Extra: ids
Provides-Extra: reranking
Requires-Dist: chromadb (>=0.4.0,<0.7.0) ; extra == "core"
Requires-Dist: httpx (>=0.27.2,<0.28.0)
Requires-Dist: llama-embedder (>=0.0.7,<0.0.8) ; extra == "embeddings"
Requires-Dist: nanoid (>=2.0.0,<3.0.0) ; extra == "ids"
Requires-Dist: pydantic (>=2.7.2,<3.0.0)
Requires-Dist: ulid-py (>=1.1.0,<2.0.0) ; extra == "ids"
Project-URL: Bug Tracker, https://github.com/amikos-tech/chromadbx/issues
Project-URL: Homepage, https://cookbook.chromadb.dev/
Project-URL: Source, https://github.com/amikos-tech/chromadbx/
